<annotation>
	<folder>FlammableLiquid</folder>
	<filename>FlammableLiquid_50.jpg</filename>
	<path>F:\HazmatlabelsBk\FlammableLiquid\FlammableLiquid_50.jpg</path>
	<source>
		<database>Unknown</database>
	</source>
	<size>
		<width>504</width>
		<height>378</height>
		<depth>3</depth>
	</size>
	<segmented>0</segmented>
	<object>
		<name>FlammableLiquid</name>
		<pose>Unspecified</pose>
		<truncated>0</truncated>
		<difficult>0</difficult>
		<bndbox>
			<xmin>170</xmin>
			<ymin>113</ymin>
			<xmax>338</xmax>
			<ymax>278</ymax>
		</bndbox>
	</object>
</annotation>
