<annotation>
	<folder>InhalationHazard</folder>
	<filename>InhalationHazard_9.jpg</filename>
	<path>C:\Users\Oriana Sampson\Desktop\Hazboi\InhalationHazard\InhalationHazard_9.jpg</path>
	<source>
		<database>Unknown</database>
	</source>
	<size>
		<width>378</width>
		<height>504</height>
		<depth>3</depth>
	</size>
	<segmented>0</segmented>
	<object>
		<name>InhalationHazard</name>
		<pose>Unspecified</pose>
		<truncated>0</truncated>
		<difficult>0</difficult>
		<bndbox>
			<xmin>86</xmin>
			<ymin>180</ymin>
			<xmax>268</xmax>
			<ymax>361</ymax>
		</bndbox>
	</object>
</annotation>
