<annotation>
	<folder>OrganicPeroxide</folder>
	<filename>OrganicPeroxide_23.jpg</filename>
	<path>C:\Users\Oriana Sampson\Desktop\Hazboi\OrganicPeroxide\OrganicPeroxide_23.jpg</path>
	<source>
		<database>Unknown</database>
	</source>
	<size>
		<width>378</width>
		<height>504</height>
		<depth>3</depth>
	</size>
	<segmented>0</segmented>
	<object>
		<name>OrganicPeroxide</name>
		<pose>Unspecified</pose>
		<truncated>0</truncated>
		<difficult>0</difficult>
		<bndbox>
			<xmin>88</xmin>
			<ymin>261</ymin>
			<xmax>289</xmax>
			<ymax>460</ymax>
		</bndbox>
	</object>
</annotation>
